context_packer.py
context_packer-1.1.5.dist-info/METADATA
context_packer-1.1.5.dist-info/WHEEL
context_packer-1.1.5.dist-info/entry_points.txt
context_packer-1.1.5.dist-info/licenses/LICENSE
context_packer-1.1.5.dist-info/RECORD
