Metadata-Version: 2.4
Name: context-packer
Version: 1.1.5
Summary: Intelligently package project directories into a single markdown file for AI analysis
Project-URL: Homepage, https://github.com/MarkShawn2020/context-packer
Project-URL: Documentation, https://github.com/MarkShawn2020/context-packer#readme
Project-URL: Repository, https://github.com/MarkShawn2020/context-packer.git
Project-URL: Issues, https://github.com/MarkShawn2020/context-packer/issues
Project-URL: Changelog, https://github.com/MarkShawn2020/context-packer/releases
Author: MarkShawn2020
Maintainer: MarkShawn2020
License: MIT
License-File: LICENSE
Keywords: ai,chatgpt,claude,code-review,context,documentation,gemini,llm,markdown,packaging,project,symlinks
Classifier: Development Status :: 5 - Production/Stable
Classifier: Environment :: Console
Classifier: Intended Audience :: Developers
Classifier: License :: OSI Approved :: MIT License
Classifier: Operating System :: OS Independent
Classifier: Programming Language :: Python :: 3
Classifier: Programming Language :: Python :: 3.8
Classifier: Programming Language :: Python :: 3.9
Classifier: Programming Language :: Python :: 3.10
Classifier: Programming Language :: Python :: 3.11
Classifier: Programming Language :: Python :: 3.12
Classifier: Topic :: Software Development :: Documentation
Classifier: Topic :: Text Processing :: Markup
Classifier: Topic :: Utilities
Requires-Python: >=3.8
